compas_libigl/_geodistance.cpython-311-darwin.so
compas_libigl/_isolines.cpython-311-darwin.so
compas_libigl/isolines.py
compas_libigl/_meshing.cpython-311-darwin.so
compas_libigl/_mapping.cpython-311-darwin.so
compas_libigl/boundaries.py
compas_libigl/_planarize.cpython-311-darwin.so
compas_libigl/_intersections.cpython-311-darwin.so
compas_libigl/massmatrix.py
compas_libigl/curvature.py
compas_libigl/_parametrisation.cpython-311-darwin.so
compas_libigl/__init__.py
compas_libigl/_boundaries.cpython-311-darwin.so
compas_libigl/intersections.py
compas_libigl/_massmatrix.cpython-311-darwin.so
compas_libigl/mapping.py
compas_libigl/parametrisation.py
compas_libigl/planarize.py
compas_libigl/meshing.py
compas_libigl/_curvature.cpython-311-darwin.so
compas_libigl/geodistance.py
include/eigen3/signature_of_eigen3_matrix_library
include/eigen3/unsupported/Eigen/MatrixFunctions
include/eigen3/unsupported/Eigen/AdolcForward
include/eigen3/unsupported/Eigen/AlignedVector3
include/eigen3/unsupported/Eigen/OpenGLSupport
include/eigen3/unsupported/Eigen/LevenbergMarquardt
include/eigen3/unsupported/Eigen/AutoDiff
include/eigen3/unsupported/Eigen/NumericalDiff
include/eigen3/unsupported/Eigen/NonLinearOptimization
include/eigen3/unsupported/Eigen/ArpackSupport
include/eigen3/unsupported/Eigen/Skyline
include/eigen3/unsupported/Eigen/BVH
include/eigen3/unsupported/Eigen/SpecialFunctions
include/eigen3/unsupported/Eigen/Splines
include/eigen3/unsupported/Eigen/KroneckerProduct
include/eigen3/unsupported/Eigen/IterativeSolvers
include/eigen3/unsupported/Eigen/FFT
include/eigen3/unsupported/Eigen/EulerAngles
include/eigen3/unsupported/Eigen/SparseExtra
include/eigen3/unsupported/Eigen/Polynomials
include/eigen3/unsupported/Eigen/MoreVectorization
include/eigen3/unsupported/Eigen/MPRealSupport
include/eigen3/unsupported/Eigen/CXX11/ThreadPool
include/eigen3/unsupported/Eigen/CXX11/TensorSymmetry
compas_libigl-0.7.6.dist-info/RECORD
compas_libigl-0.7.6.dist-info/WHEEL
compas_libigl-0.7.6.dist-info/METADATA
compas_libigl-0.7.6.dist-info/licenses/LICENSE
compas_libigl-0.7.6.dist-info/licenses/LICENSE.igl
