Metadata-Version: 2.1
Name: compas_libigl
Version: 0.7.6
Summary: libigl wrapper for COMPAS.
Author-Email: tom van mele <tom.v.mele@gmail.com>, Petras Vestartas <petrasvestartas@gmail.com>
Classifier: License :: OSI Approved :: BSD License
Project-URL: Homepage, https://compas.dev/compas_libigl/latest/
Requires-Python: >=3.9
Requires-Dist: compas>=2.0.0
Requires-Dist: tessagon
